tool/__init__.py
tool/metric/__init__.py
tool/metric/hscore.py
tool/metric/leep.py
tool/metric/logme.py
tool/metric/nce.py
tool/metric/otce.py
tool/util/__init__.py
tool/util/read_data.py
transferability_metric-0.1.dist-info/METADATA
transferability_metric-0.1.dist-info/WHEEL
transferability_metric-0.1.dist-info/top_level.txt
transferability_metric-0.1.dist-info/RECORD
