Metadata-Version: 2.1
Name: transferability-metric
Version: 0.1
Summary: My Python Package
Author: Enming Zhang
Author-email: 1229454906@qq.com
Requires-Dist: numpy (>=1.18.0)
